monty/__init__.py
monty/bisect.py
monty/collections.py
monty/design_patterns.py
monty/dev.py
monty/fnmatch.py
monty/fractions.py
monty/functools.py
monty/inspect.py
monty/io.py
monty/itertools.py
monty/json.py
monty/logging.py
monty/math.py
monty/msgpack.py
monty/multiprocessing.py
monty/operator.py
monty/pprint.py
monty/py.typed
monty/re.py
monty/serialization.py
monty/shutil.py
monty/string.py
monty/subprocess.py
monty/tempfile.py
monty/termcolor.py
monty/os/__init__.py
monty/os/path.py
monty-2025.1.3.dist-info/LICENSE.rst
monty-2025.1.3.dist-info/METADATA
monty-2025.1.3.dist-info/WHEEL
monty-2025.1.3.dist-info/top_level.txt
monty-2025.1.3.dist-info/RECORD
