Metadata-Version: 2.1
Name: monty
Version: 2025.1.3
Summary: Monty is the missing complement to Python.
Maintainer-email: Shyue Ping Ong <ongsp@ucsd.edu>
Classifier: Programming Language :: Python :: 3
Classifier: Development Status :: 4 - Beta
Classifier: Intended Audience :: Developers
Classifier: License :: OSI Approved :: MIT License
Classifier: Operating System :: OS Independent
Classifier: Topic :: Software Development :: Libraries :: Python Modules
Requires-Python: <3.14,>=3.10
License-File: LICENSE.rst
Requires-Dist: ruamel.yaml
Requires-Dist: numpy
Provides-Extra: ci
Requires-Dist: coverage; extra == "ci"
Requires-Dist: monty[optional]; extra == "ci"
Requires-Dist: pytest>=8; extra == "ci"
Requires-Dist: pytest-cov>=4; extra == "ci"
Requires-Dist: types-requests; extra == "ci"
Requires-Dist: pymongo; extra == "ci"
Provides-Extra: dev
Requires-Dist: ipython; extra == "dev"
Provides-Extra: docs
Requires-Dist: sphinx; extra == "docs"
Requires-Dist: sphinx_rtd_theme; extra == "docs"
Provides-Extra: json
Requires-Dist: pymongo; extra == "json"
Requires-Dist: orjson>=3.6.1; extra == "json"
Requires-Dist: pandas; extra == "json"
Requires-Dist: pydantic; extra == "json"
Requires-Dist: pint; python_version < "3.13" and extra == "json"
Requires-Dist: torch; python_version < "3.13" and extra == "json"
Provides-Extra: multiprocessing
Requires-Dist: tqdm; extra == "multiprocessing"
Provides-Extra: optional
Requires-Dist: monty[dev,json,multiprocessing,serialization]; extra == "optional"
Provides-Extra: serialization
Requires-Dist: msgpack; extra == "serialization"
Provides-Extra: task
Requires-Dist: requests; extra == "task"
Requires-Dist: invoke; extra == "task"
